essm/__init__.py
essm/_generator.py
essm/bases.py
essm/style.yapf
essm/transformer.py
essm/version.py
essm/equations/__init__.py
essm/equations/_core.py
essm/equations/leaf/__init__.py
essm/equations/leaf/energy_water.py
essm/equations/physics/__init__.py
essm/equations/physics/thermodynamics.py
essm/variables/__init__.py
essm/variables/_core.py
essm/variables/units.py
essm/variables/utils.py
essm/variables/chamber/__init__.py
essm/variables/chamber/insulation.py
essm/variables/chamber/mass.py
essm/variables/leaf/__init__.py
essm/variables/leaf/energy_water.py
essm/variables/leaf/radiation.py
essm/variables/physics/__init__.py
essm/variables/physics/thermodynamics.py
essm-1.1.dist-info/AUTHORS.rst
essm-1.1.dist-info/LICENSE
essm-1.1.dist-info/METADATA
essm-1.1.dist-info/WHEEL
essm-1.1.dist-info/top_level.txt
essm-1.1.dist-info/RECORD
