Metadata-Version: 2.1
Name: essm
Version: 1.1
Summary: Environmental Science using Symbolic Math.
Home-page: https://github.com/environmentalscience/essm
Author: Stan Schymanski
Author-email: schymans@gmail.com
License: GPLv2
Project-URL: Changelog, https://github.com/environmentalscience/essm/blob/master/CHANGES.rst
Project-URL: Docs, https://essm.rtfd.io/
Keywords: symbolic math environmental science
Platform: any
Classifier: License :: OSI Approved :: GNU General Public License v2 (GPLv2)
Classifier: Operating System :: OS Independent
Classifier: Programming Language :: Python
Classifier: Programming Language :: Python :: 2
Classifier: Programming Language :: Python :: 2.7
Classifier: Programming Language :: Python :: 3
Classifier: Programming Language :: Python :: 3.6
Classifier: Programming Language :: Python :: 3.7
Classifier: Development Status :: 1 - Planning
Requires-Dist: sympy (>=1.6.0)
Requires-Dist: six (>=1.10.0)
Provides-Extra: all
Requires-Dist: Sphinx (==1.8) ; extra == 'all'
Requires-Dist: matplotlib (>=1.5.1) ; extra == 'all'
Requires-Dist: sphinxcontrib-bibtex (>=0.3.5) ; extra == 'all'
Requires-Dist: nbsphinx (>=0.6.1) ; extra == 'all'
Requires-Dist: yapf (>=0.16.2) ; extra == 'all'
Requires-Dist: check-manifest (>=0.25) ; extra == 'all'
Requires-Dist: coverage (>=4.0) ; extra == 'all'
Requires-Dist: isort (>=5.0.0) ; extra == 'all'
Requires-Dist: pydocstyle (<4.0.0,>=1.0.0) ; extra == 'all'
Requires-Dist: pytest-cache (>=1.0) ; extra == 'all'
Requires-Dist: pytest-cov (>=1.8.0) ; extra == 'all'
Requires-Dist: pytest-pep8 (>=1.0.6) ; extra == 'all'
Requires-Dist: pytest (<5.0.0,>=2.8.0) ; extra == 'all'
Requires-Dist: jupyter ; extra == 'all'
Requires-Dist: nbconvert ; extra == 'all'
Requires-Dist: pandoc ; extra == 'all'
Requires-Dist: nbsphinx ; extra == 'all'
Requires-Dist: IPython ; extra == 'all'
Requires-Dist: ipykernel ; extra == 'all'
Provides-Extra: dev
Requires-Dist: jupyter ; extra == 'dev'
Requires-Dist: nbconvert ; extra == 'dev'
Requires-Dist: pandoc ; extra == 'dev'
Requires-Dist: nbsphinx ; extra == 'dev'
Requires-Dist: IPython ; extra == 'dev'
Requires-Dist: ipykernel ; extra == 'dev'
Provides-Extra: docs
Requires-Dist: Sphinx (==1.8) ; extra == 'docs'
Requires-Dist: matplotlib (>=1.5.1) ; extra == 'docs'
Requires-Dist: sphinxcontrib-bibtex (>=0.3.5) ; extra == 'docs'
Requires-Dist: nbsphinx (>=0.6.1) ; extra == 'docs'
Provides-Extra: generator
Requires-Dist: yapf (>=0.16.2) ; extra == 'generator'
Provides-Extra: tests
Requires-Dist: check-manifest (>=0.25) ; extra == 'tests'
Requires-Dist: coverage (>=4.0) ; extra == 'tests'
Requires-Dist: isort (>=5.0.0) ; extra == 'tests'
Requires-Dist: pydocstyle (<4.0.0,>=1.0.0) ; extra == 'tests'
Requires-Dist: pytest-cache (>=1.0) ; extra == 'tests'
Requires-Dist: pytest-cov (>=1.8.0) ; extra == 'tests'
Requires-Dist: pytest-pep8 (>=1.0.6) ; extra == 'tests'
Requires-Dist: pytest (<5.0.0,>=2.8.0) ; extra == 'tests'
